topstats/__init__.py
topstats/bot.py
topstats/client.py
topstats/data.py
topstats/errors.py
topstats/ratelimiter.py
topstats/version.py
topstats-1.1.3.dist-info/licenses/LICENSE
topstats-1.1.3.dist-info/METADATA
topstats-1.1.3.dist-info/WHEEL
topstats-1.1.3.dist-info/top_level.txt
topstats-1.1.3.dist-info/RECORD
