Metadata-Version: 2.4
Name: topstats
Version: 1.1.3
Summary: A simple API wrapper for topstats.gg written in Python.
Author: null8626
License: MIT
Project-URL: Documentation, https://topstats.readthedocs.io/en/latest/
Project-URL: Raw API Documentation, https://docs.topstats.gg/docs/
Project-URL: Repository, https://github.com/top-stats/python-sdk
Project-URL: Support server, https://discord.gg/jjEauJXuZc
Keywords: discord,discord-bot,topgg
Classifier: Development Status :: 5 - Production/Stable
Classifier: Intended Audience :: Developers
Classifier: Natural Language :: English
Classifier: Operating System :: OS Independent
Classifier: Programming Language :: Python :: 3 :: Only
Classifier: Programming Language :: Python :: 3.10
Classifier: Programming Language :: Python :: 3.11
Classifier: Programming Language :: Python :: 3.12
Classifier: Programming Language :: Python :: 3.13
Classifier: Programming Language :: Python :: 3.14
Classifier: Topic :: Internet
Classifier: Topic :: Software Development :: Libraries
Classifier: Topic :: Software Development :: Libraries :: Python Modules
Classifier: Topic :: Utilities
Requires-Python: >=3.10
License-File: LICENSE
Requires-Dist: aiohttp>=3.13.2
Requires-Dist: yarl>=1.22.0
Dynamic: license-file
